LICENSE.txt
MANIFEST.in
README
README.rst
requirements.txt
setup.py
django_suave.egg-info/PKG-INFO
django_suave.egg-info/SOURCES.txt
django_suave.egg-info/dependency_links.txt
django_suave.egg-info/requires.txt
django_suave.egg-info/top_level.txt
suave/__init__.py
suave/admin.py
suave/middleware.py
suave/models.py
suave/sitemap.py
suave/tests.py
suave/urls.py
suave/utils.py
suave/views.py
suave/management/__init__.py
suave/management/commands/__init__.py
suave/management/commands/create_admin.py
suave/migrations/0001_initial.py
suave/migrations/0002_auto__chg_field_page_body.py
suave/migrations/0003_auto__add_field_page_url.py
suave/migrations/0004_auto.py
suave/migrations/0005_auto.py
suave/migrations/0006_auto__add_redirect.py
suave/migrations/0007_auto__del_field_redirect_code__add_field_redirect_permanent.py
suave/migrations/0008_auto__add_field_page__page_title__add_field_page__meta_keywords__add_f.py
suave/migrations/0009_auto__del_field_navitem_show_children__add_field_navitem_added__add_fi.py
suave/migrations/0010_auto__del_field_navitem_nav.py
suave/migrations/0011_auto__chg_field_navitem_text.py
suave/migrations/0012_auto__add_pagecontent.py
suave/migrations/0013_auto__del_carouselimage__del_carousel__add_imagecarouselimage__add_ima.py
suave/migrations/0014_auto__del_field_navitem_order.py
suave/migrations/0015_auto__del_field_page_order__del_field_nav_order__del_field_pagecontent.py
suave/migrations/0016_auto__del_nav__del_field_redirect_updated__del_field_redirect_added.py
suave/migrations/0017_auto__del_attachment__add_field_navitem_template.py
suave/migrations/0018_auto__add_field_page_header_title__add_field_page_header_image__add_fi.py
suave/migrations/0019_auto__del_pagecontent__add_contentblock__del_field_page_identifier__de.py
suave/migrations/0020_auto__add_field_contentblock_added__add_field_contentblock_updated.py
suave/migrations/0021_auto__add_field_navitem_extra_classes__add_field_navitem_css_id__add_u.py
suave/migrations/0022_auto__add_field_page__page_h1.py
suave/migrations/0023_auto__del_redirect.py
suave/migrations/0024_auto__chg_field_contentblock_body__chg_field_page_body__chg_field_page.py
