Metadata-Version: 1.0
Name: django-suave
Version: 0.5.19
Summary: Rather nice pages.
Home-page: https://github.com/radiosilence/django-suave
Author: James Cleveland
Author-email: jamescleveland@gmail.com
License: LICENSE.txt
Platform: UNKNOWN
